simpledali/__init__.py
simpledali/abstractdali.py
simpledali/dali2jsonl.py
simpledali/dalipacket.py
simpledali/jsonencoder.py
simpledali/socketdali.py
simpledali/util.py
simpledali/websocketdali.py
simpledali-0.8.3.dist-info/METADATA
simpledali-0.8.3.dist-info/WHEEL
simpledali-0.8.3.dist-info/entry_points.txt
simpledali-0.8.3.dist-info/licenses/LICENSE
simpledali-0.8.3.dist-info/RECORD
