Metadata-Version: 2.4
Name: simpledali
Version: 0.8.3
Summary: Datalink protocol in python
Project-URL: Homepage, https://github.com/crotwell/simpledali
Project-URL: Documentation, https://readthedocs.org
Project-URL: Repository, https://github.com/crotwell/simpledali
Project-URL: Issues, https://github.com/crotwell/simpledali/issues
Author-email: Philip Crotwell <crotwell@seis.sc.edu>
License-File: LICENSE
Keywords: datalink,fdsn,miniseed,miniseed3,sourceid
Classifier: License :: OSI Approved :: GNU Lesser General Public License v2 or later (LGPLv2+)
Classifier: Operating System :: OS Independent
Classifier: Programming Language :: Python :: 3
Requires-Python: >=3.9
Requires-Dist: defusedxml
Requires-Dist: importlib-metadata; python_version < '3.10'
Requires-Dist: pyjwt
Requires-Dist: simplemseed>=0.4.5
Requires-Dist: tomli>=1.1.0; python_version < '3.11'
Requires-Dist: websockets
